{
  "video_id": "p0tc8I23DLA",
  "title": "GraphQL API in Astra DB - Introduction and Curl",
  "description": "We show how to perform basic Create, Read, Update and Delete (CRUD) commands, as well as how to create a table using Astra DB's Stargate GraphQL API. Check out the entire Astra playlist https://www.youtube.com/playlist?list=PL2g2h-wyI4SpWK1G3UaxXhzZc6aUFXbvL.\n\nTry using the Stargate GraphQL API with our Katacoda exercise for free here: https://katacoda.com/shallada/courses/astra-core-course/astra-graphql-api\n\nYou can find documentation on the GraphQL API here: https://docs.datastax.com/en/astra/docs/using-the-astra-graphql-api.html\n\nCONNECT WITH DATASTAX\nSubscribe: http://www.youtube.com/c/datastaxdevs?sub_confirmation=1 \nTwitter: https://twitter.com/datastaxdevs\nTwitch: https://www.twitch.tv/datastaxdevs\n\nAbout DataStax:\nDataStax is the company behind the massively scalable, highly available, cloud-native NoSQL data platform built on Apache Cassandra™. DataStax gives developers and enterprises the freedom to run data in any cloud, Kubernetes, hybrid or bare metal at global scale with zero downtime and zero lock-in. More than 450 of the world’s leading enterprises including Capital One, Cisco, Comcast, Delta Airlines, Macy’s, McDonald’s, Safeway, Sony, and Walmart use DataStax to build transformational data architectures for real-world outcomes. For more, visit DataStax.com and @DataStax.\n\nAbout DataStax Developer:\nOn the DataStax Developers YouTube channel, you can find tutorials, workshops and much more to help you learn and stay updated with the latest information on Apache Cassandra©.  Visit https://datastax.com/dev for more free learning resources.",
  "published_at": "2021-06-23T21:20:39Z",
  "thumbnail": "https://i.ytimg.com/vi/p0tc8I23DLA/maxresdefault.jpg",
  "channel_title": "DataStax Developers",
  "channel_id": "UCAIQY251avaMv7bBv5PCo-A",
  "tags": [
    "scalable",
    "workshop",
    "cassandra",
    "tutorial",
    "apache_cassandra",
    "nosql",
    "introduction",
    "astra",
    "architecture",
    "datastax"
  ],
  "url": "https://www.youtube.com/watch?v=p0tc8I23DLA",
  "transcript": {
    "available": true,
    "language": "Vietnamese (auto-generated)",
    "language_code": "vi",
    "is_generated": true,
    "text": "ừ ừ ừ ừ a story Mode support of the three bacillus cereus craftware api for your articles of Days just a word you How did you see tki ngoái cứ people wait kraftwerk eiz gladwell Hazard capaldi invented of us IS YouTube Mystery vàng giác What you want and tackling You Don't Care About making love you were strong will take what I love you going d'estate responses are not What is What's up ahead of Time enviroment variables vỏ điện thoại Acer switch user of Days dance with the connector ký được đâu views in the class to wed apr 26 of Vietnamese people chị đã với dẫn đến khuya Bố Đại còn khía corporal necessarius sport immense now go to turn on Windows in health passport time and Pearl notice that we need that Elken value of alarm at What the local people trying to be displayed with unblocked menu in the northwest Toeic organisation setting injector commencement for Navigation Channels and the Rain is waiting for the best National and Cooking Channel Token có pin và xấu kiện vay của chính here đáo cá chân mày sao mà nổ dẫu biết esther cân facial Hair Master locals and tourists I send you the export The Best Buy tiền váy mẹ phải đi được gấu Mickey euskara the table name the best their Sweet Tea party Craft you welcome and sold in the year DJ ku te Glass to word for the health and it necessary resort quickest and when you were Used the environment variables Twisted oblivious Lee Qri and valleys Where the your name your performance kia morrison Bakery nghe table first and loves is one Bad things you are and with left the wildest Steel products You Were A Prince use your dự án điện and Craft well power find the Christmas music Thank you hands for grabs you were the first hurdle in the case that occur in teaching resource and the second hand and think your verification Token will use that occurs Bis history Storm will you study that you think table name here and the table to cause must like it here is the complete clomaz notice that we paid out instakill perfectly for our work Tomorrow is Mystery mất astromart quy trình wifi a table arial ekip is Used The Theme and Find out loud noise that with the main specify the key Spirit name and fall of the adjacent Lost right dress table using Paypal comment một di sản quốc with English name is specified book is spacious and the table name với cả nước redoutable But in some countries edumax in prison is not Kill Mark kamins Instagram wenge powers file name of Pieces of the wise It's meant sama Raw a man's extraterrestre stone is different một dây xoắn wait for me instead to mars Mission in the la yeu session of j-zone width specifies that your name and advise áo sẹo We can specify the consistency Marvel industry report browse our section of the song here specify What is thus We must wear and fun to make What's You're not me it's Pretty đây will the Circle comment with recent years in prison for the word in the box Pentakill width specifies both inimitable Air permeability value investment width specifies the cause of work correctly and Earth travel A trip along but We had was the counter we make use of memories of something of the cause What lies ahead craftware What's You're the menthe now what Used with orchestra of of the last name one over What is the end turn over Vietnam history Resort within The decimal the streets on me you're Pretty the weather However as stated that matter with recent past Links from in support of people must tell you that the men Who I Can't Leave the weather trên inventor shows that which of night i I For The Vision of Recca notice that we can use That is just What to use the command and tries to streets were five armies giá show fortement I want to know more about the documentation Michael downhill hình ảnh của your awesome for more detailed explanation of the story It is the story and arts and contrast with ừ",
    "segments": [
      {
        "start": 0.0,
        "duration": 4.68,
        "text": "ừ ừ"
      },
      {
        "start": 2.44,
        "duration": 2.24,
        "text": "ừ ừ"
      },
      {
        "start": 4.85,
        "duration": 7.68,
        "text": "a story Mode support of the three"
      },
      {
        "start": 8.059,
        "duration": 8.671,
        "text": "bacillus cereus craftware api for your"
      },
      {
        "start": 12.53,
        "duration": 8.24,
        "text": "articles of Days just a word you How did"
      },
      {
        "start": 16.73,
        "duration": 8.19,
        "text": "you see tki ngoái cứ people wait"
      },
      {
        "start": 20.77,
        "duration": 9.22,
        "text": "kraftwerk eiz gladwell Hazard capaldi"
      },
      {
        "start": 24.92,
        "duration": 8.13,
        "text": "invented of us IS YouTube Mystery vàng"
      },
      {
        "start": 29.99,
        "duration": 7.259,
        "text": "giác What you want and tackling You"
      },
      {
        "start": 33.05,
        "duration": 6.87,
        "text": "Don't Care About making love you were"
      },
      {
        "start": 37.249,
        "duration": 7.551,
        "text": "strong will take what I love you going"
      },
      {
        "start": 39.92,
        "duration": 7.77,
        "text": "d'estate responses are not What is"
      },
      {
        "start": 44.8,
        "duration": 8.259,
        "text": "What's up ahead of Time enviroment"
      },
      {
        "start": 47.69,
        "duration": 11.879,
        "text": "variables vỏ điện thoại Acer switch user"
      },
      {
        "start": 53.059,
        "duration": 10.68,
        "text": "of Days dance with the connector ký được"
      },
      {
        "start": 59.569,
        "duration": 5.291,
        "text": "đâu views in the class to wed apr 26 of"
      },
      {
        "start": 63.739,
        "duration": 6.571,
        "text": "Vietnamese people"
      },
      {
        "start": 64.86,
        "duration": 10.95,
        "text": "chị đã với dẫn đến khuya Bố Đại còn khía"
      },
      {
        "start": 70.31,
        "duration": 9.01,
        "text": "corporal necessarius sport immense now"
      },
      {
        "start": 75.81,
        "duration": 9.0,
        "text": "go to turn on Windows in health passport"
      },
      {
        "start": 79.32,
        "duration": 10.92,
        "text": "time and Pearl notice that we need that"
      },
      {
        "start": 84.81,
        "duration": 8.72,
        "text": "Elken value of alarm at What the local"
      },
      {
        "start": 90.24,
        "duration": 7.34,
        "text": "people trying to be displayed with"
      },
      {
        "start": 93.53,
        "duration": 7.12,
        "text": "unblocked menu in the northwest Toeic"
      },
      {
        "start": 97.58,
        "duration": 7.6,
        "text": "organisation setting injector"
      },
      {
        "start": 100.65,
        "duration": 7.44,
        "text": "commencement for Navigation Channels and"
      },
      {
        "start": 105.18,
        "duration": 8.61,
        "text": "the Rain is waiting for the best"
      },
      {
        "start": 108.09,
        "duration": 10.02,
        "text": "National and Cooking Channel Token có"
      },
      {
        "start": 113.79,
        "duration": 7.35,
        "text": "pin và xấu kiện vay của chính here đáo"
      },
      {
        "start": 118.11,
        "duration": 5.88,
        "text": "cá chân mày sao mà nổ dẫu biết esther"
      },
      {
        "start": 121.14,
        "duration": 3.73,
        "text": "cân facial Hair Master locals and"
      },
      {
        "start": 123.99,
        "duration": 5.68,
        "text": "tourists"
      },
      {
        "start": 124.87,
        "duration": 7.56,
        "text": "I send you the export The Best Buy tiền"
      },
      {
        "start": 129.67,
        "duration": 12.93,
        "text": "váy mẹ phải đi được gấu Mickey euskara"
      },
      {
        "start": 132.43,
        "duration": 14.25,
        "text": "the table name the best their Sweet Tea"
      },
      {
        "start": 142.6,
        "duration": 9.09,
        "text": "party Craft you welcome and sold in the"
      },
      {
        "start": 146.68,
        "duration": 9.21,
        "text": "year DJ ku te Glass to word for the"
      },
      {
        "start": 151.69,
        "duration": 7.4,
        "text": "health and it necessary resort quickest"
      },
      {
        "start": 155.89,
        "duration": 7.55,
        "text": "and when you were Used the environment"
      },
      {
        "start": 159.09,
        "duration": 7.18,
        "text": "variables Twisted oblivious Lee Qri and"
      },
      {
        "start": 163.44,
        "duration": 5.89,
        "text": "valleys Where the your name your"
      },
      {
        "start": 166.27,
        "duration": 8.81,
        "text": "performance kia morrison Bakery nghe"
      },
      {
        "start": 169.33,
        "duration": 10.85,
        "text": "table first and loves is one Bad things"
      },
      {
        "start": 175.08,
        "duration": 9.77,
        "text": "you are and with left the wildest Steel"
      },
      {
        "start": 180.18,
        "duration": 8.24,
        "text": "products You Were A Prince use your"
      },
      {
        "start": 184.85,
        "duration": 12.95,
        "text": "dự án điện and Craft well power find the"
      },
      {
        "start": 188.42,
        "duration": 15.72,
        "text": "Christmas music Thank you hands for"
      },
      {
        "start": 197.8,
        "duration": 10.84,
        "text": "grabs you were the first hurdle in the"
      },
      {
        "start": 204.14,
        "duration": 6.54,
        "text": "case that occur in teaching resource and"
      },
      {
        "start": 208.64,
        "duration": 5.31,
        "text": "the second hand and think your"
      },
      {
        "start": 210.68,
        "duration": 9.26,
        "text": "verification Token will use that occurs"
      },
      {
        "start": 213.95,
        "duration": 9.96,
        "text": "Bis history Storm will you study that"
      },
      {
        "start": 219.94,
        "duration": 8.92,
        "text": "you think table name here and the table"
      },
      {
        "start": 223.91,
        "duration": 9.5,
        "text": "to cause must like it here is the"
      },
      {
        "start": 228.86,
        "duration": 8.63,
        "text": "complete clomaz notice that we paid out"
      },
      {
        "start": 233.41,
        "duration": 10.69,
        "text": "instakill perfectly for our work"
      },
      {
        "start": 237.49,
        "duration": 7.37,
        "text": "Tomorrow is Mystery mất astromart quy"
      },
      {
        "start": 244.1,
        "duration": 5.77,
        "text": "trình wifi"
      },
      {
        "start": 244.86,
        "duration": 9.95,
        "text": "a table arial ekip is Used The Theme and"
      },
      {
        "start": 249.87,
        "duration": 8.19,
        "text": "Find out loud noise that with the main"
      },
      {
        "start": 254.81,
        "duration": 9.82,
        "text": "specify the key Spirit name and fall of"
      },
      {
        "start": 258.06,
        "duration": 11.64,
        "text": "the adjacent Lost right dress table"
      },
      {
        "start": 264.63,
        "duration": 9.42,
        "text": "using Paypal comment một di sản quốc"
      },
      {
        "start": 269.7,
        "duration": 15.93,
        "text": "with English name is specified book is"
      },
      {
        "start": 274.05,
        "duration": 17.04,
        "text": "spacious and the table name với cả nước"
      },
      {
        "start": 285.63,
        "duration": 8.48,
        "text": "redoutable But in some countries edumax"
      },
      {
        "start": 291.09,
        "duration": 7.77,
        "text": "in prison is not Kill Mark kamins"
      },
      {
        "start": 294.11,
        "duration": 10.76,
        "text": "Instagram wenge powers file name of"
      },
      {
        "start": 298.86,
        "duration": 10.06,
        "text": "Pieces of the wise It's meant sama Raw"
      },
      {
        "start": 304.87,
        "duration": 8.37,
        "text": "a man's extraterrestre stone is"
      },
      {
        "start": 308.92,
        "duration": 8.46,
        "text": "different một dây xoắn wait for me"
      },
      {
        "start": 313.24,
        "duration": 7.35,
        "text": "instead to mars Mission in the la yeu"
      },
      {
        "start": 317.38,
        "duration": 8.91,
        "text": "session of j-zone width specifies that"
      },
      {
        "start": 320.59,
        "duration": 8.49,
        "text": "your name and advise áo sẹo We can"
      },
      {
        "start": 326.29,
        "duration": 6.9,
        "text": "specify the consistency Marvel industry"
      },
      {
        "start": 329.08,
        "duration": 7.77,
        "text": "report browse our section of the song"
      },
      {
        "start": 333.19,
        "duration": 7.8,
        "text": "here specify What is thus We must wear"
      },
      {
        "start": 336.85,
        "duration": 8.99,
        "text": "and fun to make What's You're not me"
      },
      {
        "start": 340.99,
        "duration": 9.35,
        "text": "it's Pretty đây will the Circle comment"
      },
      {
        "start": 345.84,
        "duration": 7.51,
        "text": "with recent years in prison for the word"
      },
      {
        "start": 350.34,
        "duration": 8.19,
        "text": "in the box Pentakill width specifies"
      },
      {
        "start": 353.35,
        "duration": 7.95,
        "text": "both inimitable Air permeability value"
      },
      {
        "start": 358.53,
        "duration": 6.319,
        "text": "investment width specifies the cause of"
      },
      {
        "start": 361.3,
        "duration": 8.53,
        "text": "work correctly and Earth travel"
      },
      {
        "start": 364.849,
        "duration": 8.22,
        "text": "A trip along but We had was the counter"
      },
      {
        "start": 369.83,
        "duration": 7.369,
        "text": "we make use of memories of something of"
      },
      {
        "start": 373.069,
        "duration": 9.451,
        "text": "the cause What lies ahead craftware"
      },
      {
        "start": 377.199,
        "duration": 9.58,
        "text": "What's You're the menthe now what Used"
      },
      {
        "start": 382.52,
        "duration": 9.379,
        "text": "with orchestra of of the last name one"
      },
      {
        "start": 386.779,
        "duration": 9.57,
        "text": "over What is the end turn over Vietnam"
      },
      {
        "start": 391.899,
        "duration": 6.841,
        "text": "history Resort within The decimal the"
      },
      {
        "start": 396.349,
        "duration": 6.03,
        "text": "streets on me you're Pretty the weather"
      },
      {
        "start": 398.74,
        "duration": 7.829,
        "text": "However as stated that matter with"
      },
      {
        "start": 402.379,
        "duration": 9.75,
        "text": "recent past Links from in support of"
      },
      {
        "start": 406.569,
        "duration": 7.81,
        "text": "people must tell you that the men Who I"
      },
      {
        "start": 412.129,
        "duration": 12.731,
        "text": "Can't Leave the weather trên inventor"
      },
      {
        "start": 414.379,
        "duration": 15.31,
        "text": "shows that which of night i"
      },
      {
        "start": 424.86,
        "duration": 9.51,
        "text": "I For The Vision of Recca notice that we"
      },
      {
        "start": 429.689,
        "duration": 8.311,
        "text": "can use That is just What to use the"
      },
      {
        "start": 434.37,
        "duration": 10.769,
        "text": "command and tries to streets were five"
      },
      {
        "start": 438.0,
        "duration": 10.319,
        "text": "armies giá show fortement I want to know"
      },
      {
        "start": 445.139,
        "duration": 11.761,
        "text": "more about the documentation Michael"
      },
      {
        "start": 448.319,
        "duration": 10.921,
        "text": "downhill hình ảnh của your awesome for"
      },
      {
        "start": 456.9,
        "duration": 7.41,
        "text": "more detailed explanation of the story"
      },
      {
        "start": 459.24,
        "duration": 12.919,
        "text": "It is the story and arts and contrast"
      },
      {
        "start": 464.31,
        "duration": 7.849,
        "text": "with ừ"
      }
    ],
    "error": null,
    "error_type": null
  },
  "collected_at": "2025-12-15T20:30:05.502454+00:00"
}